flask_rest_mongo/__init__.py
flask_rest_mongo/fields.py
flask_rest_mongo/filters.py
flask_rest_mongo/mix.py
flask_rest_mongo-0.1.5.dist-info/LICENSE
flask_rest_mongo-0.1.5.dist-info/METADATA
flask_rest_mongo-0.1.5.dist-info/WHEEL
flask_rest_mongo-0.1.5.dist-info/top_level.txt
flask_rest_mongo-0.1.5.dist-info/RECORD
