Metadata-Version: 2.1
Name: flask-rest-mongo
Version: 0.1.5
Summary: Helper utils for mongoDB in flask use flask-rest
Home-page: https://github.com/w-copper/Flask-rest-mongo.git
Author: Wang Tong
Author-email: copper.w@foxmail.com
License: UNKNOWN
Keywords: flask,mongoDB,restful
Platform: UNKNOWN
Classifier: Development Status :: 3 - Alpha
Classifier: License :: OSI Approved :: Apache Software License
Classifier: Operating System :: OS Independent
Classifier: Programming Language :: Python :: 3
Classifier: Programming Language :: Python :: 3.7
Classifier: Programming Language :: Python :: 3.8
Classifier: Topic :: Utilities
Requires-Python: >=3.7
Requires-Dist: Flask
Requires-Dist: flask-mongoengine
Requires-Dist: mongoengine
Requires-Dist: flask-restful
